SalesforceRESTAPI/SalesforceRESTAPI.py
SalesforceRESTAPI/__init__.py
salesforcerestapi-0.2.3.dist-info/licenses/LICENSE
salesforcerestapi-0.2.3.dist-info/METADATA
salesforcerestapi-0.2.3.dist-info/WHEEL
salesforcerestapi-0.2.3.dist-info/top_level.txt
salesforcerestapi-0.2.3.dist-info/RECORD
