Metadata-Version: 2.4
Name: SalesforceRESTAPI
Version: 0.2.3
Summary: A simple library to interact with Salesforce REST API using OAuth 2.0 Client Credentials Flow.
Home-page: https://github.com/arcsona/SalesforceRESTAPI
Author: Pedro Bazan
Author-email: pedro.bazan@arcsona.com
License: MIT
Classifier: Programming Language :: Python :: 3
Classifier: License :: OSI Approved :: MIT License
License-File: LICENSE
Dynamic: author
Dynamic: author-email
Dynamic: classifier
Dynamic: description
Dynamic: description-content-type
Dynamic: home-page
Dynamic: license
Dynamic: license-file
Dynamic: summary
